README.rst
hooky.py
setup.py
hooky.egg-info/PKG-INFO
hooky.egg-info/SOURCES.txt
hooky.egg-info/dependency_links.txt
hooky.egg-info/top_level.txt
test/test.py