Metadata-Version: 1.1
Name: hooky
Version: 0.5.0
Summary: A module contain list-like and a dict-like classes with hook point.
Home-page: https://github.com/meng89/hooky
Author: Chen Meng
Author-email: ObserverChan@gmail.com
License: MIT
Platform: UNKNOWN
Classifier: Intended Audience :: Developers
Classifier: License :: OSI Approved :: MIT License
Classifier: Operating System :: OS Independent
Classifier: Programming Language :: Python :: 3
Classifier: Programming Language :: Python :: 3.3
Classifier: Programming Language :: Python :: 3.4
Classifier: Programming Language :: Python :: 3.5
Classifier: Programming Language :: Python :: Implementation :: CPython
Classifier: Topic :: Software Development :: Libraries :: Python Modules
